srmudp/__init__.py
srmudp/backend.py
srmudp/common.py
srmudp/crypto_utils.py
srmudp/holepunch.py
srmudp-0.0.4.dist-info/LICENSE
srmudp-0.0.4.dist-info/METADATA
srmudp-0.0.4.dist-info/WHEEL
srmudp-0.0.4.dist-info/RECORD
