Metadata-Version: 2.1
Name: srmudp
Version: 0.0.4
Summary: 
Author: riddim
Requires-Python: >=3.11,<4.0
Classifier: Programming Language :: Python :: 3
Classifier: Programming Language :: Python :: 3.11
Classifier: Programming Language :: Python :: 3.12
Requires-Dist: pycryptodome (>=3.22.0,<4.0.0)
Requires-Dist: pytest (>=8.3.5,<9.0.0)
Requires-Dist: pyzmq (>=26.4.0,<27.0.0)
